.travis.yml
LICENSE.txt
README.rst
setup.cfg
setup.py
dockalot/__init__.py
dockalot/config.py
dockalot/docker.py
dockalot/file_util.py
dockalot.egg-info/PKG-INFO
dockalot.egg-info/SOURCES.txt
dockalot.egg-info/dependency_links.txt
dockalot.egg-info/entry_points.txt
dockalot.egg-info/requires.txt
dockalot.egg-info/top_level.txt
docs/Makefile
docs/conf.py
docs/config-reference.rst
docs/index.rst
docs/introduction.rst
examples/example1/example1.yml
examples/mysql/mysql-5.7.yml
examples/mysql/files/docker-entrypoint.sh
tests/conftest.py
tests/integration/__init__.py
tests/integration/basic.yml
tests/integration/complex.yml
tests/integration/conftest.py
tests/integration/failing.yml
tests/integration/markers.py
tests/integration/test_basics.py
tests/integration/test_docker.py
tests/integration/test_with_network.py
tests/unit/test_config.py
tests/unit/test_docker.py