Metadata-Version: 1.1
Name: dockalot
Version: 0.7.0
Summary: Build Docker images for the real world using ansible playbooks
Home-page: https://github.com/markadev/dockalot
Author: Mark Aikens
Author-email: markadev@primeletters.net
License: MIT
Platform: UNKNOWN
Classifier: Development Status :: 3 - Alpha
Classifier: Environment :: Console
Classifier: Intended Audience :: Developers
Classifier: License :: OSI Approved :: MIT License
Classifier: Operating System :: POSIX
Classifier: Programming Language :: Python
Classifier: Topic :: System :: Installation/Setup
Classifier: Topic :: Utilities
